apisession/__init__.py
apisession/apisession.py
apisession/callbacks.py
apisession/debouncer.py
apisession/throttle.py
apisession/tokenauthenticator.py
aio_apisession-0.1.10.dist-info/WHEEL
aio_apisession-0.1.10.dist-info/METADATA
aio_apisession-0.1.10.dist-info/RECORD
